<?xml version="1.0" encoding="utf-8" ?>
<dwsync>
<file name="class.radios.php" server="www.torrto.com//applications/pjercuycjs/public_html/" local="131157591800000000" remote="131157591800000000" Dst="1" />
<file name="submit.php" server="www.torrto.com//applications/pjercuycjs/public_html/" local="131157591800000000" remote="131157591800000000" Dst="1" />
<file name="class.repetitive.php" server="www.torrto.com//applications/pjercuycjs/public_html/" local="131157591800000000" remote="131157591800000000" Dst="1" />
<file name="class.colorpicker.php" server="www.torrto.com//applications/pjercuycjs/public_html/" local="131157591800000000" remote="131157591800000000" Dst="1" />
<file name="class.integer.php" server="www.torrto.com//applications/pjercuycjs/public_html/" local="131157591800000000" remote="131157591800000000" Dst="1" />
<file name="class.image.php" server="www.torrto.com//applications/pjercuycjs/public_html/" local="131157591800000000" remote="131157591800000000" Dst="1" />
<file name="class.wysiwyg.php" server="www.torrto.com//applications/pjercuycjs/public_html/" local="131157591800000000" remote="131157591800000000" Dst="1" />
<file name="class.form_factory.php" server="www.torrto.com//applications/pjercuycjs/public_html/" local="131157591800000000" remote="131157591800000000" Dst="1" />
<file name="class.conditional.php" server="www.torrto.com//applications/pjercuycjs/public_html/" local="131157591800000000" remote="131157591800000000" Dst="1" />
<file name="class.date.php" server="www.torrto.com//applications/pjercuycjs/public_html/" local="131157591800000000" remote="131157591800000000" Dst="1" />
<file name="class.field_factory.php" server="www.torrto.com//applications/pjercuycjs/public_html/" local="131157591800000000" remote="131157591800000000" Dst="1" />
<file name="abstract.form.php" server="www.torrto.com//applications/pjercuycjs/public_html/" local="131157591800000000" remote="131157591800000000" Dst="1" />
<file name="class.eforms.php" server="www.torrto.com//applications/pjercuycjs/public_html/" local="131157591800000000" remote="131157591800000000" Dst="1" />
<file name="class.textarea.php" server="www.torrto.com//applications/pjercuycjs/public_html/" local="131157591800000000" remote="131157591800000000" Dst="1" />
<file name="class.button.php" server="www.torrto.com//applications/pjercuycjs/public_html/" local="131157591800000000" remote="131157591800000000" Dst="1" />
<file name="class.url.php" server="www.torrto.com//applications/pjercuycjs/public_html/" local="131157591800000000" remote="131157591800000000" Dst="1" />
<file name="class.email.php" server="www.torrto.com//applications/pjercuycjs/public_html/" local="131157591800000000" remote="131157591800000000" Dst="1" />
<file name="class.recaptcha-v1.php" server="www.torrto.com//applications/pjercuycjs/public_html/" local="131157591800000000" remote="131157591800000000" Dst="1" />
<file name="class.validation.php" server="www.torrto.com//applications/pjercuycjs/public_html/" local="131157591800000000" remote="131157591800000000" Dst="1" />
<file name="class.credimage.php" server="www.torrto.com//applications/pjercuycjs/public_html/" local="131157591800000000" remote="131157591800000000" Dst="1" />
<file name="abstract.field.php" server="www.torrto.com//applications/pjercuycjs/public_html/" local="131157591800000000" remote="131157591800000000" Dst="1" />
<file name="class.password.php" server="www.torrto.com//applications/pjercuycjs/public_html/" local="131157591800000000" remote="131157591800000000" Dst="1" />
<file name="class.skype.php" server="www.torrto.com//applications/pjercuycjs/public_html/" local="131157591800000000" remote="131157591800000000" Dst="1" />
<file name="class.textfield.php" server="www.torrto.com//applications/pjercuycjs/public_html/" local="131157591800000000" remote="131157591800000000" Dst="1" />
<file name="class.checkbox.php" server="www.torrto.com//applications/pjercuycjs/public_html/" local="131157591800000000" remote="131157591800000000" Dst="1" />
<file name="class.types.php" server="www.torrto.com//applications/pjercuycjs/public_html/" local="131157591800000000" remote="131157591800000000" Dst="1" />
<file name="class.fieldconfig.php" server="www.torrto.com//applications/pjercuycjs/public_html/" local="131157591800000000" remote="131157591800000000" Dst="1" />
<file name="class.file.php" server="www.torrto.com//applications/pjercuycjs/public_html/" local="131157591800000000" remote="131157591800000000" Dst="1" />
<file name="class.credvideo.php" server="www.torrto.com//applications/pjercuycjs/public_html/" local="131157591800000000" remote="131157591800000000" Dst="1" />
<file name="class.audio.php" server="www.torrto.com//applications/pjercuycjs/public_html/" local="131157591800000000" remote="131157591800000000" Dst="1" />
<file name="class.select.php" server="www.torrto.com//applications/pjercuycjs/public_html/" local="131157591800000000" remote="131157591800000000" Dst="1" />
<file name="class.credfile.php" server="www.torrto.com//applications/pjercuycjs/public_html/" local="131157591800000000" remote="131157591800000000" Dst="1" />
<file name="class.taxonomyhierarchical.php" server="www.torrto.com//applications/pjercuycjs/public_html/" local="131157591800000000" remote="131157591800000000" Dst="1" />
<file name="class.taxonomy.php" server="www.torrto.com//applications/pjercuycjs/public_html/" local="131157591800000000" remote="131157591800000000" Dst="1" />
<file name="class.recaptcha.php" server="www.torrto.com//applications/pjercuycjs/public_html/" local="131157591800000000" remote="131157591800000000" Dst="1" />
<file name="class.embed.php" server="www.torrto.com//applications/pjercuycjs/public_html/" local="131157591800000000" remote="131157591800000000" Dst="1" />
<file name="class.numeric.php" server="www.torrto.com//applications/pjercuycjs/public_html/" local="131157591800000000" remote="131157591800000000" Dst="1" />
<file name="class.credaudio.php" server="www.torrto.com//applications/pjercuycjs/public_html/" local="131157591800000000" remote="131157591800000000" Dst="1" />
<file name="class.date.scripts.php" server="www.torrto.com//applications/pjercuycjs/public_html/" local="131157591800000000" remote="131157591800000000" Dst="1" />
<file name="class.checkboxes.php" server="www.torrto.com//applications/pjercuycjs/public_html/" local="131157591800000000" remote="131157591800000000" Dst="1" />
<file name="class.phone.php" server="www.torrto.com//applications/pjercuycjs/public_html/" local="131157591800000000" remote="131157591800000000" Dst="1" />
<file name="class.submit.php" server="www.torrto.com//applications/pjercuycjs/public_html/" local="131157591800000000" remote="131157591800000000" Dst="1" />
<file name="class.cred.php" server="www.torrto.com//applications/pjercuycjs/public_html/" local="131157591800000000" remote="131157591800000000" Dst="1" />
<file name="class.hidden.php" server="www.torrto.com//applications/pjercuycjs/public_html/" local="131157591800000000" remote="131157591800000000" Dst="1" />
<file name="class.video.php" server="www.torrto.com//applications/pjercuycjs/public_html/" local="131157591800000000" remote="131157591800000000" Dst="1" />
</dwsync>