<?xml version="1.0" encoding="utf-8" ?>
<dwsync>
<file name="toolset.export.import.screen.class.php" server="www.torrto.com//applications/pjercuycjs/public_html/" local="131157591800000000" remote="131157591800000000" Dst="1" />
<file name="toolset.wpml.compatibility.class.php" server="www.torrto.com//applications/pjercuycjs/public_html/" local="131157591800000000" remote="131157591800000000" Dst="1" />
<file name="toolset.menu.class.php" server="www.torrto.com//applications/pjercuycjs/public_html/" local="131157591800000000" remote="131157591800000000" Dst="1" />
<file name="toolset.settings.screen.class.php" server="www.torrto.com//applications/pjercuycjs/public_html/" local="131157591800000000" remote="131157591800000000" Dst="1" />
<file name="toolset.wplogger.class.php" server="www.torrto.com//applications/pjercuycjs/public_html/" local="131157591800000000" remote="131157591800000000" Dst="1" />
<file name="toolset.settings.class.php" server="www.torrto.com//applications/pjercuycjs/public_html/" local="131157591800000000" remote="131157591800000000" Dst="1" />
<file name="toolset.object.relationship.class.php" server="www.torrto.com//applications/pjercuycjs/public_html/" local="131157591800000000" remote="131157591800000000" Dst="1" />
<file name="toolset.assets.manager.class.php" server="www.torrto.com//applications/pjercuycjs/public_html/" local="131157591800000000" remote="131157591800000000" Dst="1" />
<file name="toolset.promotion.class.php" server="www.torrto.com//applications/pjercuycjs/public_html/" local="131157591800000000" remote="131157591800000000" Dst="1" />
<file name="toolset.compatibility.php" server="www.torrto.com//applications/pjercuycjs/public_html/" local="131157591800000000" remote="131157591800000000" Dst="1" />
<file name="toolset.function.helpers.php" server="www.torrto.com//applications/pjercuycjs/public_html/" local="131157591800000000" remote="131157591800000000" Dst="1" />
<file name="toolset.localization.class.php" server="www.torrto.com//applications/pjercuycjs/public_html/" local="131157591800000000" remote="131157591800000000" Dst="1" />
<file name="toolset.admin.bar.menu.class.php" server="www.torrto.com//applications/pjercuycjs/public_html/" local="131157591800000000" remote="131157591800000000" Dst="1" />
</dwsync>