<?xml version="1.0" encoding="utf-8" ?>
<dwsync>
<file name="bibsonomy.png" server="www.torrto.com//applications/pjercuycjs/public_html/" local="131221462640000000" remote="131221462640000000" Dst="1" />
<file name="twitter.png" server="www.torrto.com//applications/pjercuycjs/public_html/" local="131221462640000000" remote="131221462640000000" Dst="1" />
<file name="tumblr.png" server="www.torrto.com//applications/pjercuycjs/public_html/" local="131221462640000000" remote="131221462640000000" Dst="1" />
<file name="twiddla.png" server="www.torrto.com//applications/pjercuycjs/public_html/" local="131221462640000000" remote="131221462640000000" Dst="1" />
<file name="transparent.gif" server="www.torrto.com//applications/pjercuycjs/public_html/" local="131221462640000000" remote="131221462640000000" Dst="1" />
<file name="google_classroom.png" server="www.torrto.com//applications/pjercuycjs/public_html/" local="131221462640000000" remote="131221462640000000" Dst="1" />
<file name="baidu.png" server="www.torrto.com//applications/pjercuycjs/public_html/" local="131221462640000000" remote="131221462640000000" Dst="1" />
<file name="sms.png" server="www.torrto.com//applications/pjercuycjs/public_html/" local="131221462640000000" remote="131221462640000000" Dst="1" />
<file name="facebook_like.png" server="www.torrto.com//applications/pjercuycjs/public_html/" local="131221462640000000" remote="131221462640000000" Dst="1" />
<file name="delicious.png" server="www.torrto.com//applications/pjercuycjs/public_html/" local="131221462640000000" remote="131221462640000000" Dst="1" />
<file name="pinterest_pin.png" server="www.torrto.com//applications/pjercuycjs/public_html/" local="131221462640000000" remote="131221462640000000" Dst="1" />
<file name="oknotizie.png" server="www.torrto.com//applications/pjercuycjs/public_html/" local="131221462640000000" remote="131221462640000000" Dst="1" />
<file name="telegram.png" server="www.torrto.com//applications/pjercuycjs/public_html/" local="131221462640000000" remote="131221462640000000" Dst="1" />
<file name="stumpedia.png" server="www.torrto.com//applications/pjercuycjs/public_html/" local="131221462640000000" remote="131221462640000000" Dst="1" />
<file name="yummly.png" server="www.torrto.com//applications/pjercuycjs/public_html/" local="131221462640000000" remote="131221462640000000" Dst="1" />
<file name="diary_ru.png" server="www.torrto.com//applications/pjercuycjs/public_html/" local="131221462640000000" remote="131221462640000000" Dst="1" />
<file name="facebook.png" server="www.torrto.com//applications/pjercuycjs/public_html/" local="131221462640000000" remote="131221462640000000" Dst="1" />
<file name="wechat.png" server="www.torrto.com//applications/pjercuycjs/public_html/" local="131221462640000000" remote="131221462640000000" Dst="1" />
<file name="segnalo.png" server="www.torrto.com//applications/pjercuycjs/public_html/" local="131221462640000000" remote="131221462640000000" Dst="1" />
<file name="feed.png" server="www.torrto.com//applications/pjercuycjs/public_html/" local="131221462640000000" remote="131221462640000000" Dst="1" />
<file name="designfloat.png" server="www.torrto.com//applications/pjercuycjs/public_html/" local="131221462640000000" remote="131221462640000000" Dst="1" />
<file name="youtube.png" server="www.torrto.com//applications/pjercuycjs/public_html/" local="131221462640000000" remote="131221462640000000" Dst="1" />
<file name="flickr.png" server="www.torrto.com//applications/pjercuycjs/public_html/" local="131221462640000000" remote="131221462640000000" Dst="1" />
<file name="box.png" server="www.torrto.com//applications/pjercuycjs/public_html/" local="131221462640000000" remote="131221462640000000" Dst="1" />
<file name="github.png" server="www.torrto.com//applications/pjercuycjs/public_html/" local="131221462640000000" remote="131221462640000000" Dst="1" />
<file name="fark.png" server="www.torrto.com//applications/pjercuycjs/public_html/" local="131221462640000000" remote="131221462640000000" Dst="1" />
<file name="instapaper.png" server="www.torrto.com//applications/pjercuycjs/public_html/" local="131221462640000000" remote="131221462640000000" Dst="1" />
<file name="blogger.png" server="www.torrto.com//applications/pjercuycjs/public_html/" local="131221462640000000" remote="131221462640000000" Dst="1" />
<file name="tuenti.png" server="www.torrto.com//applications/pjercuycjs/public_html/" local="131221462640000000" remote="131221462640000000" Dst="1" />
<file name="mail_ru.png" server="www.torrto.com//applications/pjercuycjs/public_html/" local="131221462640000000" remote="131221462640000000" Dst="1" />
<file name="qzone.png" server="www.torrto.com//applications/pjercuycjs/public_html/" local="131221462640000000" remote="131221462640000000" Dst="1" />
<file name="trello.png" server="www.torrto.com//applications/pjercuycjs/public_html/" local="131221462640000000" remote="131221462640000000" Dst="1" />
<file name="google_plusone.png" server="www.torrto.com//applications/pjercuycjs/public_html/" local="131221462640000000" remote="131221462640000000" Dst="1" />
<file name="meneame.png" server="www.torrto.com//applications/pjercuycjs/public_html/" local="131221462640000000" remote="131221462640000000" Dst="1" />
<file name="dihitt.png" server="www.torrto.com//applications/pjercuycjs/public_html/" local="131221462640000000" remote="131221462640000000" Dst="1" />
<file name="evernote.png" server="www.torrto.com//applications/pjercuycjs/public_html/" local="131221462640000000" remote="131221462640000000" Dst="1" />
<file name="skype.png" server="www.torrto.com//applications/pjercuycjs/public_html/" local="131221462640000000" remote="131221462640000000" Dst="1" />
<file name="google_plus_share.png" server="www.torrto.com//applications/pjercuycjs/public_html/" local="131221462640000000" remote="131221462640000000" Dst="1" />
<file name="stumbleupon.png" server="www.torrto.com//applications/pjercuycjs/public_html/" local="131221462640000000" remote="131221462640000000" Dst="1" />
<file name="diigo.png" server="www.torrto.com//applications/pjercuycjs/public_html/" local="131221462640000000" remote="131221462640000000" Dst="1" />
<file name="y18.png" server="www.torrto.com//applications/pjercuycjs/public_html/" local="131221462640000000" remote="131221462640000000" Dst="1" />
<file name="blogmarks.png" server="www.torrto.com//applications/pjercuycjs/public_html/" local="131221462640000000" remote="131221462640000000" Dst="1" />
<file name="hatena.png" server="www.torrto.com//applications/pjercuycjs/public_html/" local="131221462640000000" remote="131221462640000000" Dst="1" />
<file name="yoolink.png" server="www.torrto.com//applications/pjercuycjs/public_html/" local="131221462640000000" remote="131221462640000000" Dst="1" />
<file name="bitty.png" server="www.torrto.com//applications/pjercuycjs/public_html/" local="131221462640000000" remote="131221462640000000" Dst="1" />
<file name="sitejot.png" server="www.torrto.com//applications/pjercuycjs/public_html/" local="131221462640000000" remote="131221462640000000" Dst="1" />
<file name="pusha.png" server="www.torrto.com//applications/pjercuycjs/public_html/" local="131221462640000000" remote="131221462640000000" Dst="1" />
<file name="app_net.png" server="www.torrto.com//applications/pjercuycjs/public_html/" local="131221462640000000" remote="131221462640000000" Dst="1" />
<file name="instagram.png" server="www.torrto.com//applications/pjercuycjs/public_html/" local="131221462640000000" remote="131221462640000000" Dst="1" />
<file name="typepad.png" server="www.torrto.com//applications/pjercuycjs/public_html/" local="131221462640000000" remote="131221462640000000" Dst="1" />
<file name="aol.png" server="www.torrto.com//applications/pjercuycjs/public_html/" local="131221462640000000" remote="131221462640000000" Dst="1" />
<file name="dzone.png" server="www.torrto.com//applications/pjercuycjs/public_html/" local="131221462640000000" remote="131221462640000000" Dst="1" />
<file name="slashdot.png" server="www.torrto.com//applications/pjercuycjs/public_html/" local="131221462640000000" remote="131221462640000000" Dst="1" />
<file name="mixi.png" server="www.torrto.com//applications/pjercuycjs/public_html/" local="131221462640000000" remote="131221462640000000" Dst="1" />
<file name="myspace.png" server="www.torrto.com//applications/pjercuycjs/public_html/" local="131221462640000000" remote="131221462640000000" Dst="1" />
<file name="vimeo.png" server="www.torrto.com//applications/pjercuycjs/public_html/" local="131221462640000000" remote="131221462640000000" Dst="1" />
<file name="outlook_com.png" server="www.torrto.com//applications/pjercuycjs/public_html/" local="131221462640000000" remote="131221462640000000" Dst="1" />
<file name="symbaloo.png" server="www.torrto.com//applications/pjercuycjs/public_html/" local="131221462640000000" remote="131221462640000000" Dst="1" />
<file name="wanelo.png" server="www.torrto.com//applications/pjercuycjs/public_html/" local="131221462640000000" remote="131221462640000000" Dst="1" />
<file name="pinboard.png" server="www.torrto.com//applications/pjercuycjs/public_html/" local="131221462640000000" remote="131221462640000000" Dst="1" />
<file name="kakao.png" server="www.torrto.com//applications/pjercuycjs/public_html/" local="131221462640000000" remote="131221462640000000" Dst="1" />
<file name="renren.png" server="www.torrto.com//applications/pjercuycjs/public_html/" local="131221462640000000" remote="131221462640000000" Dst="1" />
<file name="email.png" server="www.torrto.com//applications/pjercuycjs/public_html/" local="131221462640000000" remote="131221462640000000" Dst="1" />
<file name="line.png" server="www.torrto.com//applications/pjercuycjs/public_html/" local="131221462640000000" remote="131221462640000000" Dst="1" />
<file name="flipboard.png" server="www.torrto.com//applications/pjercuycjs/public_html/" local="131221462640000000" remote="131221462640000000" Dst="1" />
<file name="gmail.png" server="www.torrto.com//applications/pjercuycjs/public_html/" local="131221462640000000" remote="131221462640000000" Dst="1" />
<file name="google.png" server="www.torrto.com//applications/pjercuycjs/public_html/" local="131221462640000000" remote="131221462640000000" Dst="1" />
<file name="livejournal.png" server="www.torrto.com//applications/pjercuycjs/public_html/" local="131221462640000000" remote="131221462640000000" Dst="1" />
<file name="known.png" server="www.torrto.com//applications/pjercuycjs/public_html/" local="131221462640000000" remote="131221462640000000" Dst="1" />
<file name="plurk.png" server="www.torrto.com//applications/pjercuycjs/public_html/" local="131221462640000000" remote="131221462640000000" Dst="1" />
<file name="twitter_tweet.png" server="www.torrto.com//applications/pjercuycjs/public_html/" local="131221462640000000" remote="131221462640000000" Dst="1" />
<file name="care2.png" server="www.torrto.com//applications/pjercuycjs/public_html/" local="131221462640000000" remote="131221462640000000" Dst="1" />
<file name="mendeley.png" server="www.torrto.com//applications/pjercuycjs/public_html/" local="131221462640000000" remote="131221462640000000" Dst="1" />
<file name="foursquare.png" server="www.torrto.com//applications/pjercuycjs/public_html/" local="131221462640000000" remote="131221462640000000" Dst="1" />
<file name="print.png" server="www.torrto.com//applications/pjercuycjs/public_html/" local="131221462640000000" remote="131221462640000000" Dst="1" />
<file name="kindle.png" server="www.torrto.com//applications/pjercuycjs/public_html/" local="131221462640000000" remote="131221462640000000" Dst="1" />
<file name="svejo.png" server="www.torrto.com//applications/pjercuycjs/public_html/" local="131221462640000000" remote="131221462640000000" Dst="1" />
<file name="balatarin.png" server="www.torrto.com//applications/pjercuycjs/public_html/" local="131221462640000000" remote="131221462640000000" Dst="1" />
<file name="reddit.png" server="www.torrto.com//applications/pjercuycjs/public_html/" local="131221462640000000" remote="131221462640000000" Dst="1" />
<file name="netvouz.png" server="www.torrto.com//applications/pjercuycjs/public_html/" local="131221462640000000" remote="131221462640000000" Dst="1" />
<file name="youmob.png" server="www.torrto.com//applications/pjercuycjs/public_html/" local="131221462640000000" remote="131221462640000000" Dst="1" />
<file name="protopage.png" server="www.torrto.com//applications/pjercuycjs/public_html/" local="131221462640000000" remote="131221462640000000" Dst="1" />
<file name="link.png" server="www.torrto.com//applications/pjercuycjs/public_html/" local="131221462640000000" remote="131221462640000000" Dst="1" />
<file name="odnoklassniki.png" server="www.torrto.com//applications/pjercuycjs/public_html/" local="131221462640000000" remote="131221462640000000" Dst="1" />
<file name="printfriendly.png" server="www.torrto.com//applications/pjercuycjs/public_html/" local="131221462640000000" remote="131221462640000000" Dst="1" />
<file name="pinterest.png" server="www.torrto.com//applications/pjercuycjs/public_html/" local="131221462640000000" remote="131221462640000000" Dst="1" />
<file name="viber.png" server="www.torrto.com//applications/pjercuycjs/public_html/" local="131221462640000000" remote="131221462640000000" Dst="1" />
<file name="viadeo.png" server="www.torrto.com//applications/pjercuycjs/public_html/" local="131221462640000000" remote="131221462640000000" Dst="1" />
<file name="webnews.png" server="www.torrto.com//applications/pjercuycjs/public_html/" local="131221462640000000" remote="131221462640000000" Dst="1" />
<file name="yahoo.png" server="www.torrto.com//applications/pjercuycjs/public_html/" local="131221462640000000" remote="131221462640000000" Dst="1" />
<file name="vk.png" server="www.torrto.com//applications/pjercuycjs/public_html/" local="131221462640000000" remote="131221462640000000" Dst="1" />
<file name="yim.png" server="www.torrto.com//applications/pjercuycjs/public_html/" local="131221462640000000" remote="131221462640000000" Dst="1" />
<file name="sina_weibo.png" server="www.torrto.com//applications/pjercuycjs/public_html/" local="131221462640000000" remote="131221462640000000" Dst="1" />
<file name="buffer.png" server="www.torrto.com//applications/pjercuycjs/public_html/" local="131221462640000000" remote="131221462640000000" Dst="1" />
<file name="snapchat.png" server="www.torrto.com//applications/pjercuycjs/public_html/" local="131221462640000000" remote="131221462640000000" Dst="1" />
<file name="blinklist.png" server="www.torrto.com//applications/pjercuycjs/public_html/" local="131221462640000000" remote="131221462640000000" Dst="1" />
<file name="buddymarks.png" server="www.torrto.com//applications/pjercuycjs/public_html/" local="131221462640000000" remote="131221462640000000" Dst="1" />
<file name="nujij.png" server="www.torrto.com//applications/pjercuycjs/public_html/" local="131221462640000000" remote="131221462640000000" Dst="1" />
<file name="folkd.png" server="www.torrto.com//applications/pjercuycjs/public_html/" local="131221462640000000" remote="131221462640000000" Dst="1" />
<file name="diaspora.png" server="www.torrto.com//applications/pjercuycjs/public_html/" local="131221462640000000" remote="131221462640000000" Dst="1" />
<file name="default.png" server="www.torrto.com//applications/pjercuycjs/public_html/" local="131221462640000000" remote="131221462640000000" Dst="1" />
<file name="pocket.png" server="www.torrto.com//applications/pjercuycjs/public_html/" local="131221462640000000" remote="131221462640000000" Dst="1" />
<file name="behance.png" server="www.torrto.com//applications/pjercuycjs/public_html/" local="131221462640000000" remote="131221462640000000" Dst="1" />
<file name="netlog.png" server="www.torrto.com//applications/pjercuycjs/public_html/" local="131221462640000000" remote="131221462640000000" Dst="1" />
<file name="wordpress.png" server="www.torrto.com//applications/pjercuycjs/public_html/" local="131221462640000000" remote="131221462640000000" Dst="1" />
<file name="xing.png" server="www.torrto.com//applications/pjercuycjs/public_html/" local="131221462640000000" remote="131221462640000000" Dst="1" />
<file name="kik.png" server="www.torrto.com//applications/pjercuycjs/public_html/" local="131221462640000000" remote="131221462640000000" Dst="1" />
<file name="whatsapp.png" server="www.torrto.com//applications/pjercuycjs/public_html/" local="131221462640000000" remote="131221462640000000" Dst="1" />
<file name="citeulike.png" server="www.torrto.com//applications/pjercuycjs/public_html/" local="131221462640000000" remote="131221462640000000" Dst="1" />
<file name="wykop.png" server="www.torrto.com//applications/pjercuycjs/public_html/" local="131221462640000000" remote="131221462640000000" Dst="1" />
<file name="rediff.png" server="www.torrto.com//applications/pjercuycjs/public_html/" local="131221462640000000" remote="131221462640000000" Dst="1" />
<file name="bookmarks_fr.png" server="www.torrto.com//applications/pjercuycjs/public_html/" local="131221462640000000" remote="131221462640000000" Dst="1" />
<file name="draugiem.png" server="www.torrto.com//applications/pjercuycjs/public_html/" local="131221462640000000" remote="131221462640000000" Dst="1" />
<file name="amazon.png" server="www.torrto.com//applications/pjercuycjs/public_html/" local="131221462640000000" remote="131221462640000000" Dst="1" />
<file name="bookmark.png" server="www.torrto.com//applications/pjercuycjs/public_html/" local="131221462640000000" remote="131221462640000000" Dst="1" />
<file name="douban.png" server="www.torrto.com//applications/pjercuycjs/public_html/" local="131221462640000000" remote="131221462640000000" Dst="1" />
<file name="facebook_messenger.png" server="www.torrto.com//applications/pjercuycjs/public_html/" local="131221462640000000" remote="131221462640000000" Dst="1" />
<file name="newsvine.png" server="www.torrto.com//applications/pjercuycjs/public_html/" local="131221462640000000" remote="131221462640000000" Dst="1" />
<file name="jamespot.png" server="www.torrto.com//applications/pjercuycjs/public_html/" local="131221462640000000" remote="131221462640000000" Dst="1" />
<file name="digg.png" server="www.torrto.com//applications/pjercuycjs/public_html/" local="131221462640000000" remote="131221462640000000" Dst="1" />
<file name="linkedin.png" server="www.torrto.com//applications/pjercuycjs/public_html/" local="131221462640000000" remote="131221462640000000" Dst="1" />
<file name="aim.png" server="www.torrto.com//applications/pjercuycjs/public_html/" local="131221462640000000" remote="131221462640000000" Dst="1" />
<file name="google_plus.png" server="www.torrto.com//applications/pjercuycjs/public_html/" local="131221462640000000" remote="131221462640000000" Dst="1" />
</dwsync>